getsong
