Metadata-Version: 1.1
Name: getsong
Version: 2.0.0
Summary: A Python program which uses BeautifulSoup and Youtube-dl to download a song from youtube
Home-page: https://blha303.github.io/getsong/
Author: Steven Smith
Author-email: stevensmith.ome@gmail.com
License: MIT
Platform: UNKNOWN
Classifier: Development Status :: 4 - Beta
Classifier: License :: OSI Approved :: MIT License
Classifier: Programming Language :: Python :: 3.4
Classifier: Programming Language :: Python :: 3
Classifier: Intended Audience :: End Users/Desktop
Classifier: Intended Audience :: System Administrators
Classifier: Topic :: Multimedia :: Sound/Audio
